{"cameraMode":{"drawMode":0,"name":"Shaded","section":"Shading Mode"},"sceneLighting":true,"audioPlay":false,"sceneViewState":{"showFog":true,"showMaterialUpdate":false,"showSkybox":true,"showFlares":true,"showImageEffects":true,"showParticleSystems":true},"in2DMode":false,"pivot":{"x":13.283049583435059,"y":-0.34301257133483889,"z":0.2101229429244995},"rotation":{"x":-0.09391538798809052,"y":0.6518979072570801,"z":-0.08185151219367981,"w":-0.7480036020278931},"size":13.95151424407959,"orthographic":false}